bu_course_cli/__init__.py
bu_course_cli/app.py
bu_course_cli/cli.py
bu_course_cli-0.1.1.dist-info/METADATA
bu_course_cli-0.1.1.dist-info/WHEEL
bu_course_cli-0.1.1.dist-info/entry_points.txt
bu_course_cli-0.1.1.dist-info/top_level.txt
bu_course_cli-0.1.1.dist-info/RECORD
