Metadata-Version: 2.1
Name: bu-course-cli
Version: 0.1.1
Requires-Dist: Flask
Requires-Dist: requests
